acailib/Annotator.py
acailib/Concept.py
acailib/EntityReader.py
acailib/__init__.py
acailib/importance/baseimportance.py
acailib/importance/peopleimportance.py
acailib/lexicon/LexiconEntry.py
acailib/lexicon/__init__.py
acailib/lexicon/lemmatizer.py
acailib/lexicon/serializer.py
acailib/lexicon/ubsdgnt.py
acailib/render/Entity.py
acailib/render/__init__.py
acailib/shared_classes.py
acailib/util/Categorizer.py
acailib/util/Language.py
acailib/util/TSVReader.py
acailib/util/TyndaleReader.py
acailib/util/__init__.py
acailib/util/license.py
acailib/util/macula.py
acailib/util/marble.py
acailib/util/strongs.py
acailib/util/util.py
acailib-0.1.5.dist-info/METADATA
acailib-0.1.5.dist-info/WHEEL
acailib-0.1.5.dist-info/RECORD
